README.md
py_cachify/__init__.py
py_cachify/py.typed
py_cachify/_backend/__init__.py
py_cachify/_backend/_cached.py
py_cachify/_backend/_clients.py
py_cachify/_backend/_constants.py
py_cachify/_backend/_exceptions.py
py_cachify/_backend/_helpers.py
py_cachify/_backend/_lib.py
py_cachify/_backend/_lock.py
py_cachify/_backend/_logger.py
py_cachify/_backend/_types/__init__.py
py_cachify/_backend/_types/_common.py
py_cachify/_backend/_types/_lock_wrap.py
py_cachify/_backend/_types/_reset_wrap.py
py_cachify-3.0.1.dist-info/METADATA
py_cachify-3.0.1.dist-info/WHEEL
py_cachify-3.0.1.dist-info/licenses/LICENSE
py_cachify-3.0.1.dist-info/RECORD
